ml_research_toolkit/__init__.py
ml_research_toolkit/datasets/__init__.py
ml_research_toolkit/datasets/uci.py
ml_research_toolkit/notifications/__init__.py
ml_research_toolkit/notifications/telegram_client.py
ml_research_toolkit-0.0.5.dist-info/LICENSE
ml_research_toolkit-0.0.5.dist-info/METADATA
ml_research_toolkit-0.0.5.dist-info/WHEEL
ml_research_toolkit-0.0.5.dist-info/top_level.txt
ml_research_toolkit-0.0.5.dist-info/RECORD
