Metadata-Version: 2.1
Name: ml-research-toolkit
Version: 0.0.5
Summary: toolkits for machine learning, python package
Home-page: https://github.com/andriygav/MLResearchToolkit
Author: Andrey Grabovoy
Author-email: grabovoy.av@phystech.edu
License: MIT
Platform: UNKNOWN
Requires-Python: ==3.*
License-File: LICENSE
Requires-Dist: python-telegram-bot (==12.8)
Requires-Dist: html5lib (==1.0.1)
Requires-Dist: bs4 (==0.0.1)
Requires-Dist: pandas (==1.1.5)
